lndocs/__init__.py
lndocs/__main__.py
lndocs/_generate_conf.py
lndocs/_postprocess.py
lndocs/_template_conf.py
lndocs/lamin_sphinx/__init__.py
lndocs/lamin_sphinx/_authors.py
lndocs/lamin_sphinx/_cite_commands.py
lndocs/lamin_sphinx/_footnote_title.py
lndocs/lamin_sphinx/_front_matter.py
lndocs/lamin_sphinx/_nitpick_ignore.py
lndocs/lamin_sphinx/_sort_autosummary.py
lndocs/lamin_sphinx/_static/custom.css
lndocs/lamin_sphinx/_static/img/favicon.ico
lndocs/lamin_sphinx/_static/img/logo.png
lndocs/lamin_sphinx/_static/img/logo.svg
lndocs/lamin_sphinx/_templates/collection.html
lndocs/lamin_sphinx/_templates/docs-navbar.html
lndocs/lamin_sphinx/_templates/footer.html
lndocs/lamin_sphinx/_templates/layout.html
lndocs/lamin_sphinx/_templates/navbar-logo.html
lndocs/lamin_sphinx/_templates/page-toc.html
lndocs/lamin_sphinx/_templates/postnavy.html
lndocs/lamin_sphinx/_templates/prev-next.html
lndocs/lamin_sphinx/_templates/recentposts.html
lndocs/lamin_sphinx/_templates/theme-switcher.html
lndocs/lamin_sphinx/_templates/autosummary/class.rst
lndocs/lamin_sphinx/_templates/autosummary/module.rst
lndocs-0.3.0.dist-info/entry_points.txt
lndocs-0.3.0.dist-info/WHEEL
lndocs-0.3.0.dist-info/METADATA
lndocs-0.3.0.dist-info/RECORD
